{
	"$schema": "https://schemas.wp.org/trunk/block.json",
	"apiVersion": 3,
	"name": "of/hero-showcase",
	"version": "0.1.0",
	"title": "Hero Showcase",
	"category": "media",
	"icon": "format-image",
	"description": "フルビューポート対応のヒーローブロック",
	"supports": {
		"align": ["full"],
		"html": false
	},
	"attributes": {
		"fullViewport": {
			"type": "boolean",
			"default": false
		}
	},
	"textdomain": "ns-media-hero-showcase",
	"editorScript": "file:./index.js",
	"editorStyle": "file:./editor.css",
	"style": "file:./style.css"
}